paperclip/__init__.py
paperclip/admin.py
paperclip/forms.py
paperclip/models.py
paperclip/settings.py
paperclip/urls.py
paperclip/utils.py
paperclip/validators.py
paperclip/views.py
paperclip/locale/en/LC_MESSAGES/django.mo
paperclip/locale/fr/LC_MESSAGES/django.mo
paperclip/static/paperclip/bootstrap-3-confirm.js
paperclip/static/paperclip/bootstrap-4-confirm.js
paperclip/static/paperclip/bootstrap-confirm.js
paperclip/static/paperclip/paperclip.js
paperclip/static/paperclip/spin.min.js
paperclip/static/paperclip/star-off.svg
paperclip/static/paperclip/star-on.svg
paperclip/static/paperclip/fileicons/7z.png
paperclip/static/paperclip/fileicons/ai.png
paperclip/static/paperclip/fileicons/aiff.png
paperclip/static/paperclip/fileicons/asc.png
paperclip/static/paperclip/fileicons/audio.png
paperclip/static/paperclip/fileicons/bin.png
paperclip/static/paperclip/fileicons/bz2.png
paperclip/static/paperclip/fileicons/c.png
paperclip/static/paperclip/fileicons/cfc.png
paperclip/static/paperclip/fileicons/cfm.png
paperclip/static/paperclip/fileicons/chm.png
paperclip/static/paperclip/fileicons/class.png
paperclip/static/paperclip/fileicons/conf.png
paperclip/static/paperclip/fileicons/cpp.png
paperclip/static/paperclip/fileicons/cs.png
paperclip/static/paperclip/fileicons/css.png
paperclip/static/paperclip/fileicons/csv.png
paperclip/static/paperclip/fileicons/deb.png
paperclip/static/paperclip/fileicons/divx.png
paperclip/static/paperclip/fileicons/doc.png
paperclip/static/paperclip/fileicons/dot.png
paperclip/static/paperclip/fileicons/eml.png
paperclip/static/paperclip/fileicons/enc.png
paperclip/static/paperclip/fileicons/file.png
paperclip/static/paperclip/fileicons/gif.png
paperclip/static/paperclip/fileicons/gpx.png
paperclip/static/paperclip/fileicons/gz.png
paperclip/static/paperclip/fileicons/hlp.png
paperclip/static/paperclip/fileicons/htm.png
paperclip/static/paperclip/fileicons/html.png
paperclip/static/paperclip/fileicons/image.png
paperclip-2.7.3.dist-info/LICENSE
paperclip-2.7.3.dist-info/METADATA
paperclip-2.7.3.dist-info/WHEEL
paperclip-2.7.3.dist-info/top_level.txt
paperclip-2.7.3.dist-info/RECORD
